<?xml version="1.0" encoding="utf-8" ?>
<!--
 * Copyright (c) 2005-2021 The OPC Foundation, Inc. All rights reserved.
 *
 * OPC Foundation MIT License 1.00
 * 
 * Permission is hereby granted, free of charge, to any person
 * obtaining a copy of this software and associated documentation
 * files (the "Software"), to deal in the Software without
 * restriction, including without limitation the rights to use,
 * copy, modify, merge, publish, distribute, sublicense, and/or sell
 * copies of the Software, and to permit persons to whom the
 * Software is furnished to do so, subject to the following
 * conditions:
 * 
 * The above copyright notice and this permission notice shall be
 * included in all copies or substantial portions of the Software.
 * THE SOFTWARE IS PROVIDED "AS IS", WITHOUT WARRANTY OF ANY KIND,
 * EXPRESS OR IMPLIED, INCLUDING BUT NOT LIMITED TO THE WARRANTIES
 * OF MERCHANTABILITY, FITNESS FOR A PARTICULAR PURPOSE AND
 * NONINFRINGEMENT. IN NO EVENT SHALL THE AUTHORS OR COPYRIGHT
 * HOLDERS BE LIABLE FOR ANY CLAIM, DAMAGES OR OTHER LIABILITY,
 * WHETHER IN AN ACTION OF CONTRACT, TORT OR OTHERWISE, ARISING
 * FROM, OUT OF OR IN CONNECTION WITH THE SOFTWARE OR THE USE OR
 * OTHER DEALINGS IN THE SOFTWARE.
 *
 * The complete license agreement can be found here:
 * http://opcfoundation.org/License/MIT/1.00/
-->

<UANodeSet xmlns:xsd="http://www.w3.org/2001/XMLSchema" xmlns:xsi="http://www.w3.org/2001/XMLSchema-instance" LastModified="2021-01-21T00:00:00Z" xmlns="http://opcfoundation.org/UA/2011/03/UANodeSet.xsd">
  <Models>
    <Model ModelUri="http://opcfoundation.org/UA/" Version="1.04.9" PublicationDate="2021-01-21T00:00:00Z" />
  </Models>
    <!-- SKS nodes (TODO: add types) -->
  <UAObject BrowseName="PublishSubscribe" NodeId="i=14443">
    <DisplayName>PublishSubscribe</DisplayName>
    <Description>The base type for all object nodes.</Description>
    <References>
      <Reference IsForward="false" ReferenceType="HasComponent">i=2253</Reference>
      <Reference ReferenceType="HasTypeDefinition">i=58</Reference>
      <Reference ReferenceType="HasComponent">i=15215</Reference>
   </References>
  </UAObject>
  <UAMethod BrowseName="GetSecurityKeys" NodeId="i=15215" MethodDeclarationId="">
    <DisplayName>GetSecurityKeys</DisplayName>
    <Description>GetSecurityKeys</Description>
    <References>
      <Reference ReferenceType="HasProperty">i=15216</Reference>
      <Reference ReferenceType="HasProperty">i=15217</Reference>
    </References>
  </UAMethod>
  <UAVariable BrowseName="InputArguments" DataType="i=296" NodeId="i=15216" ValueRank="1">
    <DisplayName>InputArguments</DisplayName>
    <References>
      <Reference ReferenceType="HasTypeDefinition">i=68</Reference>
    </References>
    <Value>
      <ListOfExtensionObject xmlns="http://opcfoundation.org/UA/2008/02/Types.xsd">
        <ExtensionObject>
          <TypeId>
            <Identifier>i=297</Identifier>
          </TypeId>
          <Body>
            <Argument>
              <Name>SecurityGroupId</Name>
              <DataType>
                <Identifier>i=12</Identifier>
              </DataType>
              <ValueRank>-1</ValueRank>
              <ArrayDimensions />
            </Argument>
          </Body>
        </ExtensionObject>
        <ExtensionObject>
          <TypeId>
            <Identifier>i=297</Identifier>
          </TypeId>
          <Body>
            <Argument>
              <Name>StartingTokenId</Name>
              <DataType>
                <Identifier>i=7</Identifier>
              </DataType>
              <ValueRank>-1</ValueRank>
              <ArrayDimensions />
            </Argument>
          </Body>
        </ExtensionObject>
        <ExtensionObject>
          <TypeId>
            <Identifier>i=297</Identifier>
          </TypeId>
          <Body>
            <Argument>
              <Name>RequestedKeyCount</Name>
              <DataType>
                <Identifier>i=7</Identifier>
              </DataType>
              <ValueRank>-1</ValueRank>
              <ArrayDimensions />
            </Argument>
          </Body>
          </ExtensionObject>
      </ListOfExtensionObject>
    </Value>
  </UAVariable>
  <UAVariable BrowseName="OutputArguments" DataType="i=296" NodeId="i=15217" ValueRank="1">
    <DisplayName>OutputArguments</DisplayName>
    <References>
      <Reference ReferenceType="HasTypeDefinition">i=68</Reference>
    </References>
    <Value>
        <ListOfExtensionObject xmlns="http://opcfoundation.org/UA/2008/02/Types.xsd">
        <ExtensionObject>
          <TypeId>
            <Identifier>i=297</Identifier>
          </TypeId>
          <Body>
            <Argument>
              <Name>SecurityPolicyUri</Name>
              <DataType>
                <Identifier>i=12</Identifier>
              </DataType>
              <ValueRank>-1</ValueRank>
              <ArrayDimensions />
            </Argument>
          </Body>
        </ExtensionObject>
        <ExtensionObject>
          <TypeId>
            <Identifier>i=297</Identifier>
          </TypeId>
          <Body>
            <Argument>
              <Name>FirstTokenId</Name>
              <DataType>
                <Identifier>i=288</Identifier>
              </DataType>
              <ValueRank>-1</ValueRank>
              <ArrayDimensions />
            </Argument>
          </Body>
        </ExtensionObject>
        <ExtensionObject>
          <TypeId>
            <Identifier>i=297</Identifier>
          </TypeId>
          <Body>
            <Argument>
              <Name>Keys</Name>
              <DataType>
                <Identifier>i=15</Identifier>
              </DataType>
              <ValueRank>1</ValueRank>
              <ArrayDimensions />
            </Argument>
          </Body>
        </ExtensionObject>
        <ExtensionObject>
          <TypeId>
            <Identifier>i=297</Identifier>
          </TypeId>
          <Body>
            <Argument>
              <Name>TimeToNextKey</Name>
              <DataType>
                <Identifier>i=290</Identifier>
              </DataType>
              <ValueRank>-1</ValueRank>
              <ArrayDimensions />
            </Argument>
          </Body>
        </ExtensionObject>
        <ExtensionObject>
          <TypeId>
            <Identifier>i=297</Identifier>
          </TypeId>
          <Body>
            <Argument>
              <Name>KeyLifetime</Name>
              <DataType>
                <Identifier>i=290</Identifier>
              </DataType>
              <ValueRank>-1</ValueRank>
              <ArrayDimensions />
            </Argument>
          </Body>
        </ExtensionObject>
      </ListOfExtensionObject>
    </Value>
  </UAVariable>
</UANodeSet>
